BottleJwtAuth-21.9.1.data/data/examples/app.py
JwtAuth/JWKS.py
JwtAuth/__init__.py
JwtAuth/bottle_utils.py
JwtAuth/jwtAuth.py
BottleJwtAuth-21.9.1.dist-info/LICENSE.txt
BottleJwtAuth-21.9.1.dist-info/METADATA
BottleJwtAuth-21.9.1.dist-info/WHEEL
BottleJwtAuth-21.9.1.dist-info/top_level.txt
BottleJwtAuth-21.9.1.dist-info/RECORD
