Metadata-Version: 2.1
Name: BottleJwtAuth
Version: 21.9.1
Summary: JWT authentication plugin for Bottle
Home-page: https://github.com/Glocktober/JwtAuth
Author: gunville
Author-email: rk13088@yahoo.com
License: UNKNOWN
Project-URL: repo, https://github.com/Glocktober/JwtAuth
Project-URL: overview, https://github.com/Glocktober/JwtAuth/blob/main/README.md
Keywords: 'bottle jwt oidc plugin'
Platform: UNKNOWN
Classifier: Programming Language :: Python :: 3
Classifier: License :: OSI Approved :: MIT License
Classifier: Operating System :: OS Independent
Classifier: Framework :: Bottle
Requires-Python: >=3.6
License-File: LICENSE.txt
Requires-Dist: JwtEncoder (>=21.8)
Requires-Dist: bottle (>=0.12.0)
